superchat/__init__.py
superchat/main.py
superchat/config/models.json
superchat/core/__init__.py
superchat/core/chat.py
superchat/core/command_handler.py
superchat/core/message_handler.py
superchat/core/message_router.py
superchat/core/model_client.py
superchat/core/session.py
superchat/core/setup.py
superchat/core/staged_flow.py
superchat/ui/__init__.py
superchat/ui/display.py
superchat/utils/__init__.py
superchat/utils/api_key_wizard.py
superchat/utils/cli.py
superchat/utils/debug.py
superchat/utils/fuzzy_matcher.py
superchat/utils/identifiers.py
superchat/utils/model_resolver.py
superchat/utils/naming.py
superchat/utils/parser.py
superchat/utils/stats.py
superchat-0.10.dist-info/licenses/LICENSE
superchat-0.10.dist-info/METADATA
superchat-0.10.dist-info/WHEEL
superchat-0.10.dist-info/entry_points.txt
superchat-0.10.dist-info/top_level.txt
superchat-0.10.dist-info/RECORD
