Metadata-Version: 2.4
Name: superchat
Version: 0.10
Summary: AI-driven discussions and multi-agent debates
Author: superchat
Project-URL: Homepage, https://github.com/shukmeister/superchat
Project-URL: Repository, https://github.com/shukmeister/superchat.git
Keywords: ai,chat,cli,autogen,multi-agent
Classifier: Development Status :: 3 - Alpha
Classifier: Intended Audience :: Developers
Classifier: Programming Language :: Python :: 3
Classifier: Programming Language :: Python :: 3.8
Classifier: Programming Language :: Python :: 3.9
Classifier: Programming Language :: Python :: 3.10
Classifier: Programming Language :: Python :: 3.11
Classifier: Programming Language :: Python :: 3.12
Requires-Python: >=3.8
License-File: LICENSE
Requires-Dist: autogen-agentchat>=0.4.0
Requires-Dist: autogen-ext[openai]>=0.4.0
Requires-Dist: python-dotenv>=1.0.0
Requires-Dist: halo>=0.0.31
Requires-Dist: prompt_toolkit>=3.0.0
Dynamic: license-file
